femder/BEM_3D.py
femder/BoundaryConditions.py
femder/FEM_1D.py
femder/FEM_3D.py
femder/GeometryGenerate.py
femder/__init__.py
femder/controlsair.py
femder/fem_numerical.py
femder/grid_importing.py
femder/optimization_helpers.py
femder/plot_tools.py
femder/rayinidir.py
femder/receivers.py
femder/sources.py
femder/utils.py
femder-0.2.0.dist-info/LICENSE.md
femder-0.2.0.dist-info/METADATA
femder-0.2.0.dist-info/WHEEL
femder-0.2.0.dist-info/top_level.txt
femder-0.2.0.dist-info/RECORD
