Metadata-Version: 2.1
Name: femder
Version: 0.2.0
Summary: A simple acoustic FEM package
Author-email: Luiz Augusto Alvim <luiz.alvim@eac.ufsm.br>
Project-URL: Homepage, https://github.com/jvcarli/femder
Project-URL: Bug Tracker, https://github.com/jvcarli/femder/issues
Classifier: Programming Language :: Python :: 3
Classifier: License :: OSI Approved :: MIT License
Classifier: Operating System :: OS Independent
Requires-Python: <3.12,>=3.9
License-File: LICENSE.md
Requires-Dist: cloudpickle
Requires-Dist: gmsh
Requires-Dist: ipython
Requires-Dist: kaleido
Requires-Dist: matplotlib
Requires-Dist: meshio
Requires-Dist: mkl
Requires-Dist: numba <0.59
Requires-Dist: numpy
Requires-Dist: plotly >=4.9
Requires-Dist: psutil
Requires-Dist: pyMKL2
Requires-Dist: pymoo
Requires-Dist: pytta
Requires-Dist: scipy
Requires-Dist: seaborn
Requires-Dist: tmma
Requires-Dist: tqdm
Provides-Extra: dev
Requires-Dist: sphinx-autobuild ; extra == 'dev'
Requires-Dist: pydata-sphinx-theme ; extra == 'dev'
Requires-Dist: sphinx ; extra == 'dev'
Requires-Dist: ruff ; extra == 'dev'
Provides-Extra: dev_doc
Requires-Dist: sphinx-autobuild ; extra == 'dev_doc'
Provides-Extra: doc
Requires-Dist: pydata-sphinx-theme ; extra == 'doc'
Requires-Dist: sphinx ; extra == 'doc'
Provides-Extra: lint
Requires-Dist: ruff ; extra == 'lint'
